nodeconductor_organization/__init__.py
nodeconductor_organization/admin.py
nodeconductor_organization/apps.py
nodeconductor_organization/extension.py
nodeconductor_organization/filters.py
nodeconductor_organization/handlers.py
nodeconductor_organization/models.py
nodeconductor_organization/permissions.py
nodeconductor_organization/serializers.py
nodeconductor_organization/urls.py
nodeconductor_organization/views.py
nodeconductor_organization/migrations/0001_initial.py
nodeconductor_organization/migrations/0002_change_customer_field.py
nodeconductor_organization/migrations/__init__.py
nodeconductor_organization-0.3.0.dist-info/top_level.txt
nodeconductor_organization-0.3.0.dist-info/entry_points.txt
nodeconductor_organization-0.3.0.dist-info/METADATA
nodeconductor_organization-0.3.0.dist-info/DESCRIPTION.rst
nodeconductor_organization-0.3.0.dist-info/metadata.json
nodeconductor_organization-0.3.0.dist-info/WHEEL
nodeconductor_organization-0.3.0.dist-info/RECORD
