Metadata-Version: 2.0
Name: nodeconductor-organization
Version: 0.3.0
Summary: NodeConductor Organization management plugin
Home-page: http://nodeconductor.com
Author: OpenNode Team
Author-email: info@opennodecloud.com
License: UNKNOWN
Platform: UNKNOWN
Classifier: Framework :: Django
Classifier: Intended Audience :: Developers
Classifier: Intended Audience :: System Administrators
Classifier: Operating System :: OS Independent
Classifier: License :: OSI Approved :: MIT License
Requires-Dist: nodeconductor (>=0.107.0)
Provides-Extra: dev
Requires-Dist: Sphinx (==1.2.2); extra == 'dev'
